bordado/__init__.py
bordado/_distance.py
bordado/_grid.py
bordado/_line.py
bordado/_profile.py
bordado/_random.py
bordado/_region.py
bordado/_split.py
bordado/_utils.py
bordado/_validation.py
bordado/_version.py
bordado-0.4.0.dist-info/licenses/AUTHORS.md
bordado-0.4.0.dist-info/licenses/LICENSE.txt
bordado-0.4.0.dist-info/METADATA
bordado-0.4.0.dist-info/WHEEL
bordado-0.4.0.dist-info/top_level.txt
bordado-0.4.0.dist-info/RECORD
