Metadata-Version: 2.4
Name: bordado
Version: 0.4.0
Summary: Create, manipulate, and split geographic coordinates
Author-email: The Bordado Developers <fatiandoaterra@protonmail.com>
Maintainer-email: Leonardo Uieda <leo@uieda.com>
License: BSD-3-Clause
Project-URL: Documentation, https://www.fatiando.org/bordado
Project-URL: Changelog, https://www.fatiando.org/bordado/latest/changes.html
Project-URL: Bug Tracker, https://github.com/fatiando/bordado/issues
Project-URL: Source Code, https://github.com/fatiando/bordado
Keywords: geoscience,geophysics
Classifier: Development Status :: 2 - Pre-Alpha
Classifier: Intended Audience :: Science/Research
Classifier: Intended Audience :: Developers
Classifier: Intended Audience :: Education
Classifier: License :: OSI Approved :: BSD License
Classifier: Natural Language :: English
Classifier: Operating System :: OS Independent
Classifier: Programming Language :: Python :: 3
Classifier: Programming Language :: Python :: 3.9
Classifier: Programming Language :: Python :: 3.10
Classifier: Programming Language :: Python :: 3.11
Classifier: Programming Language :: Python :: 3.12
Classifier: Programming Language :: Python :: 3.13
Classifier: Topic :: Scientific/Engineering
Classifier: Topic :: Software Development :: Libraries
Requires-Python: >=3.9
License-File: LICENSE.txt
License-File: AUTHORS.md
Requires-Dist: numpy>=1.23
Requires-Dist: scipy>=1.8
Dynamic: license-file
